{
  "v": "5.7.4",
  "fr": 30,
  "ip": 0,
  "op": 90,
  "w": 280,
  "h": 400,
  "nm": "Taif PNG placeholder",
  "ddd": 0,
  "assets": [
    {
      "id": "image_0",
      "w": 280,
      "h": 400,
      "u": "assets/taif/",
      "p": "transparent/confident.png",
      "e": 0
    }
  ],
  "layers": [
    {
      "ddd": 0,
      "ind": 1,
      "ty": 2,
      "nm": "Taif",
      "refId": "image_0",
      "sr": 1,
      "ks": {
        "o": {
          "a": 0,
          "k": 100
        },
        "r": {
          "a": 0,
          "k": 0
        },
        "p": {
          "a": 0,
          "k": [
            140,
            200,
            0
          ]
        },
        "a": {
          "a": 0,
          "k": [
            140,
            200,
            0
          ]
        },
        "s": {
          "a": 0,
          "k": [
            100,
            100,
            100
          ]
        }
      },
      "ao": 0,
      "ip": 0,
      "op": 90,
      "st": 0,
      "bm": 0
    }
  ],
  "markers": [
    {
      "cm": "idle",
      "tm": 0,
      "dr": 90
    },
    {
      "cm": "walk",
      "tm": 0,
      "dr": 90
    },
    {
      "cm": "talk",
      "tm": 0,
      "dr": 90
    },
    {
      "cm": "count",
      "tm": 0,
      "dr": 90
    },
    {
      "cm": "react_bad",
      "tm": 0,
      "dr": 90
    },
    {
      "cm": "react_good",
      "tm": 0,
      "dr": 90
    }
  ]
}